mechrheo/__init__.py
mechrheo/fitdata.py
mechrheo/models.py
mechrheo/plot.py
mechrheo-0.1.0.dist-info/AUTHORS.rst
mechrheo-0.1.0.dist-info/LICENSE
mechrheo-0.1.0.dist-info/METADATA
mechrheo-0.1.0.dist-info/WHEEL
mechrheo-0.1.0.dist-info/top_level.txt
mechrheo-0.1.0.dist-info/RECORD
