Metadata-Version: 2.1
Name: mechrheo
Version: 0.1.0
Summary: Python toolbox for rheology
Home-page: https://github.com/mecheng/mechrheo
Author: Jelle Spijker
Author-email: spijker.jelle@gmail.com
License: MIT license
Keywords: mechrheo
Platform: UNKNOWN
Classifier: Development Status :: 2 - Pre-Alpha
Classifier: Intended Audience :: Developers
Classifier: License :: OSI Approved :: MIT License
Classifier: Natural Language :: English
Classifier: Programming Language :: Python :: 3
Classifier: Programming Language :: Python :: 3.4
Classifier: Programming Language :: Python :: 3.5
Classifier: Programming Language :: Python :: 3.6
Classifier: Programming Language :: Python :: 3.7
Requires-Dist: numpy
Requires-Dist: scipy
Requires-Dist: pint
Requires-Dist: matplotlib
